{
  "slug": "stress-anxiety-management",
  "title": "Stress & Anxiety Management",
  "subtitle": "Mental Wellness Program",
  "metaTitle": "Stress & Anxiety Management | Vaidyam Healthcare",
  "metaDescription": "Discover Ayurvedic stress and anxiety support through calming therapies, meditation, herbal care, and a balanced lifestyle plan.",
  "summary": "We help calm the nervous system through a blend of therapeutic practices, mindful routines, and herbal support.",
  "highlights": [
    "Mind-body wellness support",
    "Meditation and breathing practices",
    "Herbal support for stress",
    "Personalized calm-building plan"
  ],
  "benefits": [
    "Improved sleep",
    "Better emotional balance",
    "Reduced mental fatigue",
    "Greater resilience"
  ],
  "treatmentSteps": [
    "Stress assessment",
    "Therapy selection",
    "Daily calming practices",
    "Progress tracking"
  ]
}
